djangocms_multisite/__init__.py
djangocms_multisite/middleware.py
djangocms_multisite/models.py
djangocms_multisite-0.3.1.dist-info/LICENSE
djangocms_multisite-0.3.1.dist-info/METADATA
djangocms_multisite-0.3.1.dist-info/WHEEL
djangocms_multisite-0.3.1.dist-info/top_level.txt
djangocms_multisite-0.3.1.dist-info/RECORD
