Metadata-Version: 2.1
Name: djangocms-multisite
Version: 0.3.1
Summary: django-multisite supporto for django CMS
Home-page: https://github.com/nephila/djangocms-multisite
Author: Iacopo Spalletti
Author-email: i.spalletti@nephila.it
License: BSD
Keywords: djangocms-multisite,django
Platform: UNKNOWN
Classifier: Development Status :: 3 - Alpha
Classifier: Framework :: Django
Classifier: Intended Audience :: Developers
Classifier: License :: OSI Approved :: BSD License
Classifier: Natural Language :: English
Classifier: Framework :: Django
Classifier: Framework :: Django :: 2.2
Classifier: Framework :: Django :: 3.0
Classifier: Programming Language :: Python :: 3
Classifier: Programming Language :: Python :: 3.5
Classifier: Programming Language :: Python :: 3.6
Classifier: Programming Language :: Python :: 3.7
Classifier: Programming Language :: Python :: 3.8
Requires-Dist: django-multisite
Requires-Dist: django-cms
